smof/__init__.py
smof/functions.py
smof/ui.py
smof/version.py
smof-2.22.4.dist-info/LICENSE
smof-2.22.4.dist-info/METADATA
smof-2.22.4.dist-info/WHEEL
smof-2.22.4.dist-info/entry_points.txt
smof-2.22.4.dist-info/top_level.txt
smof-2.22.4.dist-info/RECORD
