Metadata-Version: 2.1
Name: smof
Version: 2.22.4
Summary: UNIX-style utilities for FASTA file exploration
Home-page: https://github.com/incertae-sedis/smof
Author: Zebulun Arendsee
Author-email: zbwrnz@gmail.com
Classifier: Programming Language :: Python :: 3
Classifier: License :: OSI Approved :: MIT License
Classifier: Operating System :: OS Independent
License-File: LICENSE
